qiskit/VERSION.txt
qiskit/__init__.py
qiskit/_accelerate.pyd
qiskit/_qasm2.pyd
qiskit/exceptions.py
qiskit/execute_function.py
qiskit/namespace.py
qiskit/user_config.py
qiskit/version.py
qiskit/algorithms/__init__.py
qiskit/algorithms/algorithm_job.py
qiskit/algorithms/algorithm_result.py
qiskit/algorithms/aux_ops_evaluator.py
qiskit/algorithms/exceptions.py
qiskit/algorithms/list_or_dict.py
qiskit/algorithms/observables_evaluator.py
qiskit/algorithms/variational_algorithm.py
qiskit/algorithms/amplitude_amplifiers/__init__.py
qiskit/algorithms/amplitude_amplifiers/amplification_problem.py
qiskit/algorithms/amplitude_amplifiers/amplitude_amplifier.py
qiskit/algorithms/amplitude_amplifiers/grover.py
qiskit/algorithms/amplitude_estimators/__init__.py
qiskit/algorithms/amplitude_estimators/ae.py
qiskit/algorithms/amplitude_estimators/ae_utils.py
qiskit/algorithms/amplitude_estimators/amplitude_estimator.py
qiskit/algorithms/amplitude_estimators/estimation_problem.py
qiskit/algorithms/amplitude_estimators/fae.py
qiskit/algorithms/amplitude_estimators/iae.py
qiskit/algorithms/amplitude_estimators/mlae.py
qiskit/algorithms/eigen_solvers/__init__.py
qiskit/algorithms/eigen_solvers/eigen_solver.py
qiskit/algorithms/eigen_solvers/numpy_eigen_solver.py
qiskit/algorithms/eigen_solvers/vqd.py
qiskit/algorithms/eigensolvers/__init__.py
qiskit/algorithms/eigensolvers/eigensolver.py
qiskit/algorithms/eigensolvers/numpy_eigensolver.py
qiskit/algorithms/eigensolvers/vqd.py
qiskit/algorithms/evolvers/__init__.py
qiskit/algorithms/evolvers/evolution_problem.py
qiskit/algorithms/evolvers/evolution_result.py
qiskit/algorithms/evolvers/imaginary_evolver.py
qiskit/algorithms/evolvers/real_evolver.py
qiskit/algorithms/evolvers/trotterization/__init__.py
qiskit/algorithms/evolvers/trotterization/trotter_qrte.py
qiskit/algorithms/gradients/__init__.py
qiskit/algorithms/gradients/qfi.py
qiskit/algorithms/gradients/qfi_result.py
qiskit/algorithms/gradients/utils.py
artur_qiskit_terra-0.45.2.dist-info/LICENSE.txt
artur_qiskit_terra-0.45.2.dist-info/METADATA
artur_qiskit_terra-0.45.2.dist-info/WHEEL
artur_qiskit_terra-0.45.2.dist-info/entry_points.txt
artur_qiskit_terra-0.45.2.dist-info/top_level.txt
artur_qiskit_terra-0.45.2.dist-info/RECORD
