Metadata-Version: 2.1
Name: artur-qiskit-terra
Version: 0.45.2
Summary: Software for developing quantum computing programs
Home-page: https://github.com/Qiskit/qiskit
Author: Qiskit Development Team
Author-email: hello@qiskit.org
License: Apache 2.0
Project-URL: Bug Tracker, https://github.com/Qiskit/qiskit-terra/issues
Project-URL: Documentation, https://qiskit.org/documentation/
Project-URL: Source Code, https://github.com/Qiskit/qiskit-terra
Keywords: qiskit sdk quantum
Classifier: Environment :: Console
Classifier: License :: OSI Approved :: Apache Software License
Classifier: Intended Audience :: Developers
Classifier: Intended Audience :: Science/Research
Classifier: Operating System :: Microsoft :: Windows
Classifier: Operating System :: MacOS
Classifier: Operating System :: POSIX :: Linux
Classifier: Programming Language :: Python :: 3 :: Only
Classifier: Programming Language :: Python :: 3.8
Classifier: Programming Language :: Python :: 3.9
Classifier: Programming Language :: Python :: 3.10
Classifier: Programming Language :: Python :: 3.11
Classifier: Programming Language :: Python :: 3.12
Classifier: Topic :: Scientific/Engineering
Requires-Python: >=3.8
License-File: LICENSE.txt
Requires-Dist: rustworkx >=0.13.0
Requires-Dist: numpy <2,>=1.17
Requires-Dist: ply >=3.10
Requires-Dist: psutil >=5
Requires-Dist: scipy >=1.5
Requires-Dist: sympy >=1.3
Requires-Dist: dill >=0.3
Requires-Dist: python-dateutil >=2.8.0
Requires-Dist: stevedore >=3.0.0
Requires-Dist: symengine !=0.10.0,>=0.9 ; platform_machine == "x86_64" or platform_machine == "aarch64" or platform_machine == "ppc64le" or platform_machine == "amd64" or platform_machine == "arm64"
Requires-Dist: typing-extensions ; python_version < "3.11"
Provides-Extra: all
Requires-Dist: matplotlib >=3.3 ; extra == 'all'
Requires-Dist: ipywidgets >=7.3.0 ; extra == 'all'
Requires-Dist: pydot ; extra == 'all'
Requires-Dist: pillow >=4.2.1 ; extra == 'all'
Requires-Dist: pylatexenc >=1.4 ; extra == 'all'
Requires-Dist: seaborn >=0.9.0 ; extra == 'all'
Requires-Dist: pygments >=2.4 ; extra == 'all'
Requires-Dist: z3-solver >=4.7 ; extra == 'all'
Requires-Dist: python-constraint >=1.4 ; extra == 'all'
Requires-Dist: qiskit-qasm3-import >=0.1.0 ; extra == 'all'
Provides-Extra: crosstalk-pass
Requires-Dist: z3-solver >=4.7 ; extra == 'crosstalk-pass'
Provides-Extra: csp-layout-pass
Requires-Dist: python-constraint >=1.4 ; extra == 'csp-layout-pass'
Provides-Extra: qasm3-import
Requires-Dist: qiskit-qasm3-import >=0.1.0 ; extra == 'qasm3-import'
Provides-Extra: visualization
Requires-Dist: matplotlib >=3.3 ; extra == 'visualization'
Requires-Dist: ipywidgets >=7.3.0 ; extra == 'visualization'
Requires-Dist: pydot ; extra == 'visualization'
Requires-Dist: pillow >=4.2.1 ; extra == 'visualization'
Requires-Dist: pylatexenc >=1.4 ; extra == 'visualization'
Requires-Dist: seaborn >=0.9.0 ; extra == 'visualization'
Requires-Dist: pygments >=2.4 ; extra == 'visualization'
